msgapi/__init__.py
msgapi/cli.py
msgapi/config.py
msgapi/functions.py
msgapi/etc/graph_config.ini
msgapi/etc/msgapi_config.ini
msgapi/etc/resource_configuration_template.ini
msgapi/resource_configurations/get_secureScore.ini
msgapi/resource_configurations/get_security_alert.ini
msgapi/resource_configurations/get_user.ini
msgapi/resource_configurations/history_of_riskyUser.ini
msgapi/resource_configurations/list_secureScores.ini
msgapi/resource_configurations/list_security_alerts.ini
msgapi/resource_configurations/list_signIns.ini
msgapi/resource_configurations/riskyUsers.ini
msgapi-1.0.0.data/scripts/msgraphi
msgapi-1.0.0.dist-info/METADATA
msgapi-1.0.0.dist-info/WHEEL
msgapi-1.0.0.dist-info/top_level.txt
msgapi-1.0.0.dist-info/RECORD
