Metadata-Version: 2.1
Name: msgapi
Version: 1.0.0
Summary: A library and cli tool for interfacing with Microsoft's Graph API.
Home-page: https://github.com/ace-ecosystem/msgapi
Author: Sean McFeely
Author-email: mcfeelynaes@gmail.com
License: Apache-2.0
Keywords: Information Security,Microsoft,GraphAPI,graph api
Platform: UNKNOWN
Classifier: Development Status :: 5 - Production/Stable
Classifier: Intended Audience :: Developers
Classifier: Intended Audience :: Information Technology
Classifier: Intended Audience :: Telecommunications Industry
Classifier: Operating System :: OS Independent
Classifier: License :: OSI Approved :: Apache Software License
Classifier: Programming Language :: Python :: 3 :: Only
Classifier: Programming Language :: Python :: 3
Requires-Dist: argcomplete
Requires-Dist: coloredlogs
Requires-Dist: configparser
Requires-Dist: msal
Requires-Dist: requests
